mswp/__init__.py
mswp/mswp.py
mswp-1.0.0.dist-info/LICENSE
mswp-1.0.0.dist-info/METADATA
mswp-1.0.0.dist-info/WHEEL
mswp-1.0.0.dist-info/top_level.txt
mswp-1.0.0.dist-info/RECORD
