Metadata-Version: 2.1
Name: mswp
Version: 1.0.0
Summary: A decorator that automatically clears temporary local variables upon function execution, effectively preventing clutter and mitigating memory leaks.
Keywords: decorator,memory,memory-leaks,performance,variables,security,scalling
Classifier: Programming Language :: Python
Classifier: Programming Language :: Python :: 3
Classifier: Intended Audience :: Education
Classifier: Intended Audience :: Science/Research
Classifier: License :: OSI Approved :: Apache Software License
Classifier: Topic :: Scientific/Engineering
Classifier: Topic :: Scientific/Engineering :: Artificial Intelligence
Classifier: Topic :: Software Development
Classifier: Topic :: Software Development :: Libraries
Classifier: Topic :: Software Development :: Libraries :: Python Modules
License-File: LICENSE
